hecss/__init__.py
hecss/_nbdev.py
hecss/cli.py
hecss/core.py
hecss/monitor.py
hecss-0.5.0.2.dist-info/COPYING
hecss-0.5.0.2.dist-info/LICENSE
hecss-0.5.0.2.dist-info/METADATA
hecss-0.5.0.2.dist-info/WHEEL
hecss-0.5.0.2.dist-info/entry_points.txt
hecss-0.5.0.2.dist-info/top_level.txt
hecss-0.5.0.2.dist-info/RECORD
