Metadata-Version: 2.1
Name: hecss
Version: 0.5.0.2
Summary: High Efficiency Configuration Space Sampler
Home-page: https://gitlab.com/jochym/hecss/tree/devel/
Author: Paweł T. Jochym
Author-email: pawel.jochym@ifj.edu.pl
License: GNU General Public License ver. 3
Keywords: physics temperature configurations
Classifier: Development Status :: 5 - Production/Stable
Classifier: Intended Audience :: Science/Research
Classifier: License :: OSI Approved :: GNU General Public License v3 (GPLv3)
Classifier: Natural Language :: English
Classifier: Programming Language :: Python :: 3.6
Classifier: Programming Language :: Python :: 3.7
Classifier: Programming Language :: Python :: 3.8
Requires-Python: >=3.6
License-File: LICENSE
License-File: COPYING
Requires-Dist: ase
Requires-Dist: spglib
Requires-Dist: tqdm
Requires-Dist: click
Requires-Dist: matplotlib
Requires-Dist: numpy
Requires-Dist: scipy
Requires-Dist: ipython
